brena/__init__.py
brena/__main__.py
brena/calculation.py
brena/cli.py
brena/commands.py
brena/config.py
brena/currency.py
brena/i18n.py
brena/invoice_templates/__init__.py
brena/invoice_templates/invoice.html
brena/jinja/__init__.py
brena/jinja/filters.py
brena/jinja/utils.py
brena/rendering.py
brena-0.0.2.dist-info/entry_points.txt
brena-0.0.2.dist-info/WHEEL
brena-0.0.2.dist-info/METADATA
brena-0.0.2.dist-info/RECORD
