Metadata-Version: 2.1
Name: brena
Version: 0.0.2
Summary: Simple invoice generation.
Home-page: https://grski.pl/
License: MIT
Keywords: invoice,invoice generator,brena
Author: Olaf Górski
Requires-Python: >=3.9,<4.0
Classifier: License :: OSI Approved :: MIT License
Classifier: Programming Language :: Python :: 3
Classifier: Programming Language :: Python :: 3.9
Requires-Dist: WeasyPrint (>=52.1,<53.0)
Requires-Dist: jinja2 (>=2.11.1,<3.0.0)
Requires-Dist: toml (>=0.10.0,<0.11.0)
Requires-Dist: typer (>=0.3.2,<0.4.0)
Project-URL: Documentation, https://github.com/grski/brena
Project-URL: Repository, https://github.com/grski/brena
